{
  "type": "Feature",
  "properties": {
    "gn:admin1_code":"0.0",
    "gn:asciiname":"Lejone",
    "gn:country_code":"LS",
    "gn:dem":2189,
    "gn:feature_class":"P",
    "gn:feature_code":"PPL",
    "gn:name":"Lejone",
    "gn:population":0,
    "gn:timezone":"Africa/Maseru",
    "iso:country":"LS",
    "wof:name":"Lejone",
    "wof:placetype":"locality"
},
  "geometry": {"coordinates":[28.48807,-29.10853],"type":"Point"}
}