{
  "type": "Feature",
  "properties": {
    "gn:admin1_code":"19.0",
    "gn:asciiname":"Ha Thoso",
    "gn:country_code":"LS",
    "gn:dem":2582,
    "gn:feature_class":"P",
    "gn:feature_code":"PPL",
    "gn:name":"Ha Thoso",
    "gn:population":0,
    "gn:timezone":"Africa/Maseru",
    "iso:country":"LS",
    "wof:name":"Ha Thoso",
    "wof:placetype":"locality"
},
  "geometry": {"coordinates":[28.744,-29.405],"type":"Point"}
}