{
  "type": "Feature",
  "properties": {
    "iso:country":"LS",
    "name:afr_x_preferred":[
        "Teyateyaneng"
    ],
    "name:ara_x_preferred":[
        "\u062a\u064a\u0627\u062a\u064a\u0627\u0646\u064a\u0646\u063a"
    ],
    "name:bre_x_preferred":[
        "Teyateyaneng"
    ],
    "name:deu_x_preferred":[
        "Teyateyaneng"
    ],
    "name:eng_x_preferred":[
        "Teyateyaneng"
    ],
    "name:fra_x_preferred":[
        "Teyateyaneng"
    ],
    "name:frr_x_preferred":[
        "Teyateyaneng"
    ],
    "name:heb_x_preferred":[
        "\u05d8\u05d9\u05d0\u05d8\u05d9\u05d0\u05e0\u05e0\u05d2"
    ],
    "name:hrv_x_preferred":[
        "Teyateyaneng"
    ],
    "name:hun_x_preferred":[
        "Teyateyaneng"
    ],
    "name:ita_x_preferred":[
        "Teyateyaneng"
    ],
    "name:jpn_x_preferred":[
        "\u30c6\u30e4\u30c6\u30e4\u30cd\u30f3\u30b0"
    ],
    "name:lit_x_preferred":[
        "Tejatejanengas"
    ],
    "name:nld_x_preferred":[
        "Teyateyaneng"
    ],
    "name:nob_x_preferred":[
        "Teyateyaneng"
    ],
    "name:nor_x_preferred":[
        "Teyateyaneng"
    ],
    "name:pol_x_preferred":[
        "Teyateyaneng"
    ],
    "name:por_x_preferred":[
        "Teyateyaneng"
    ],
    "name:ron_x_preferred":[
        "Teyateyaneng"
    ],
    "name:rus_x_preferred":[
        "\u0422\u0435\u044f\u0442\u0435\u044f\u043d\u0435\u043d\u0433"
    ],
    "name:sot_x_preferred":[
        "Teyateyaneng"
    ],
    "name:spa_x_preferred":[
        "Teyateyaneng"
    ],
    "name:swe_x_preferred":[
        "Teyateyaneng"
    ],
    "name:ukr_x_preferred":[
        "\u0422\u0435\u044f\u0442\u0435\u044f\u043d\u0435\u043d\u0433"
    ],
    "name:urd_x_preferred":[
        "\u062a\u0626\u06cc\u0627\u062a\u0626\u06cc\u0627\u0646\u06af"
    ],
    "name:zho_x_preferred":[
        "\u6cf0\u4e9e\u6cf0\u4e9e\u5ae9"
    ],
    "qs:gn_pop":0,
    "qs:name":"Teyateyaneng",
    "qs:name_adm0":"Lesotho",
    "qs:name_adm1":"Berea",
    "qs:photos":6,
    "qs:photos_1k":1,
    "qs:photos_9k":1,
    "qs:photos_9r":1,
    "qs:photos_all":6,
    "qs:photos_sr":1,
    "qs:placetype":"Town",
    "qs:pop_sr":"0",
    "qs:woe_adm0":23424880,
    "wd:wordcount":464,
    "wof:name":"Teyateyaneng",
    "wof:placetype":"locality"
},
  "geometry": {"coordinates":[27.747559,-29.150549],"type":"Point"}
}