{
  "type": "Feature",
  "properties": {
    "gn:admin1_code":"0.0",
    "gn:asciiname":"Thakabannas Cattle Post",
    "gn:country_code":"LS",
    "gn:dem":2741,
    "gn:feature_class":"P",
    "gn:feature_code":"PPL",
    "gn:name":"Thakabannas Cattle Post",
    "gn:population":0,
    "gn:timezone":"Africa/Maseru",
    "iso:country":"LS",
    "wof:name":"Thakabannas Cattle Post",
    "wof:placetype":"locality"
},
  "geometry": {"coordinates":[28.65,-28.75],"type":"Point"}
}