{
  "type": "Feature",
  "properties": {
    "gn:admin1_code":"0.0",
    "gn:asciiname":"Ha Nohana",
    "gn:country_code":"LS",
    "gn:dem":1699,
    "gn:feature_class":"P",
    "gn:feature_code":"PPL",
    "gn:name":"Ha Nohana",
    "gn:population":0,
    "gn:timezone":"Africa/Maseru",
    "iso:country":"LS",
    "name:und_x_variant":[
        "Na Nohama",
        "Ha Nohana"
    ],
    "wof:name":"Ha Nohana",
    "wof:placetype":"locality"
},
  "geometry": {"coordinates":[27.85378,-30.05371],"type":"Point"}
}