{
  "type": "Feature",
  "properties": {
    "gn:admin1_code":"0.0",
    "gn:asciiname":"Malibe",
    "gn:country_code":"LS",
    "gn:dem":1724,
    "gn:feature_class":"P",
    "gn:feature_code":"PPL",
    "gn:name":"Malibe",
    "gn:population":0,
    "gn:timezone":"Africa/Maseru",
    "iso:country":"LS",
    "name:und_x_variant":[
        "Madibe",
        "Malibe"
    ],
    "wof:name":"Malibe",
    "wof:placetype":"locality"
},
  "geometry": {"coordinates":[27.93577,-30.24886],"type":"Point"}
}