{
  "type": "Feature",
  "properties": {
    "gn:admin1_code":"0.0",
    "gn:asciiname":"Matela",
    "gn:country_code":"LS",
    "gn:dem":1772,
    "gn:feature_class":"P",
    "gn:feature_code":"PPL",
    "gn:name":"Matela",
    "gn:population":0,
    "gn:timezone":"Africa/Maseru",
    "iso:country":"LS",
    "name:ceb_x_preferred":[
        "Matela"
    ],
    "name:deu_x_preferred":[
        "Matela"
    ],
    "name:fra_x_preferred":[
        "Matela"
    ],
    "name:new_x_preferred":[
        "\u092e\u0924\u0947\u0932\u093e"
    ],
    "name:nld_x_preferred":[
        "Matela"
    ],
    "name:pol_x_preferred":[
        "Matela"
    ],
    "name:por_x_preferred":[
        "Matela"
    ],
    "name:rus_x_preferred":[
        "\u041c\u0430\u0442\u0435\u043b\u0430"
    ],
    "name:ukr_x_preferred":[
        "\u041c\u0430\u0442\u0435\u043b\u0430"
    ],
    "name:und_x_variant":[
        "Matelas",
        "Khotsa"
    ],
    "wof:name":"Matela",
    "wof:placetype":"locality"
},
  "geometry": {"coordinates":[27.76764,-29.37502000000001],"type":"Point"}
}