{
  "type": "Feature",
  "properties": {
    "gn:admin1_code":"0.0",
    "gn:asciiname":"Matela",
    "gn:country_code":"LS",
    "gn:dem":1772,
    "gn:feature_class":"P",
    "gn:feature_code":"PPL",
    "gn:name":"Matela",
    "gn:population":0,
    "gn:timezone":"Africa/Maseru",
    "iso:country":"LS",
    "name:und_x_variant":[
        "Matelas",
        "Khotsa",
        "Matela"
    ],
    "wof:name":"Matela",
    "wof:placetype":"locality"
},
  "geometry": {"coordinates":[27.76764,-29.37502000000001],"type":"Point"}
}