{
  "type": "Feature",
  "properties": {
    "gn:admin1_code":"14.0",
    "gn:asciiname":"Ha Paki",
    "gn:country_code":"LS",
    "gn:dem":1571,
    "gn:feature_class":"P",
    "gn:feature_code":"PPLF",
    "gn:name":"Ha Paki",
    "gn:population":0,
    "gn:timezone":"Africa/Maseru",
    "iso:country":"LS",
    "wof:name":"Ha Paki",
    "wof:placetype":"locality"
},
  "geometry": {"coordinates":[27.5559,-29.4103],"type":"Point"}
}