{
  "type": "Feature",
  "properties": {
    "gn:admin1_code":"0.0",
    "gn:asciiname":"Mokhathis",
    "gn:cc2":"LS",
    "gn:country_code":"LS",
    "gn:dem":1594,
    "gn:feature_class":"P",
    "gn:feature_code":"PPL",
    "gn:name":"Mokhathis",
    "gn:population":0,
    "gn:timezone":"Africa/Maseru",
    "iso:country":"LS",
    "name:und_x_variant":[
        "Makati",
        "Mokhathis"
    ],
    "wof:name":"Mokhathis",
    "wof:placetype":"locality"
},
  "geometry": {"coordinates":[27.95,-29.11667000000001],"type":"Point"}
}