{
  "type": "Feature",
  "properties": {
    "gn:admin1_code":"0.0",
    "gn:asciiname":"Mokoeng",
    "gn:country_code":"LS",
    "gn:dem":2190,
    "gn:feature_class":"P",
    "gn:feature_code":"PPL",
    "gn:name":"Mokoeng",
    "gn:population":0,
    "gn:timezone":"Africa/Maseru",
    "iso:country":"LS",
    "name:und_x_variant":[
        "Tlokoeng",
        "Mokoeng"
    ],
    "wof:name":"Mokoeng",
    "wof:placetype":"locality"
},
  "geometry": {"coordinates":[28.90116,-29.24077],"type":"Point"}
}