{
  "type": "Feature",
  "properties": {
    "gn:admin1_code":"0.0",
    "gn:asciiname":"Patrick",
    "gn:country_code":"LS",
    "gn:dem":2121,
    "gn:feature_class":"P",
    "gn:feature_code":"PPL",
    "gn:name":"Patrick",
    "gn:population":0,
    "gn:timezone":"Africa/Maseru",
    "iso:country":"LS",
    "name:cat_x_preferred":[
        "Patrick"
    ],
    "name:ceb_x_preferred":[
        "Patrick"
    ],
    "name:deu_x_preferred":[
        "Patrick"
    ],
    "name:ell_x_preferred":[
        "\u03a0\u03b1\u03c4\u03c1\u03af\u03ba\u03b9\u03bf\u03c2"
    ],
    "name:heb_x_preferred":[
        "\u05e4\u05d8\u05e8\u05d9\u05e7"
    ],
    "name:ita_x_preferred":[
        "Patrick"
    ],
    "name:kor_x_preferred":[
        "\ud328\ud2b8\ub9ad"
    ],
    "name:nld_x_preferred":[
        "Patrick"
    ],
    "name:pol_x_preferred":[
        "Patrick"
    ],
    "name:por_x_preferred":[
        "Patrick"
    ],
    "name:spa_x_preferred":[
        "Patrick"
    ],
    "name:srp_x_preferred":[
        "\u041f\u0430\u0442\u0440\u0438\u043a"
    ],
    "name:swe_x_preferred":[
        "Patrick"
    ],
    "name:und_x_variant":[
        "Saint Patrick"
    ],
    "wof:name":"Patrick",
    "wof:placetype":"locality"
},
  "geometry": {"coordinates":[27.74409,-29.52606],"type":"Point"}
}