{
  "type": "Feature",
  "properties": {
    "gn:admin1_code":"0.0",
    "gn:asciiname":"Patrick",
    "gn:country_code":"LS",
    "gn:dem":2121,
    "gn:feature_class":"P",
    "gn:feature_code":"PPL",
    "gn:name":"Patrick",
    "gn:population":0,
    "gn:timezone":"Africa/Maseru",
    "iso:country":"LS",
    "name:und_x_variant":[
        "Saint Patrick",
        "Patrick"
    ],
    "wof:name":"Patrick",
    "wof:placetype":"locality"
},
  "geometry": {"coordinates":[27.74409,-29.52606],"type":"Point"}
}