{
  "type": "Feature",
  "properties": {
    "gn:admin1_code":"0.0",
    "gn:asciiname":"Berea Hills",
    "gn:country_code":"LS",
    "gn:dem":1610,
    "gn:feature_class":"P",
    "gn:feature_code":"PPL",
    "gn:name":"Berea Hills",
    "gn:population":0,
    "gn:timezone":"Africa/Maseru",
    "iso:country":"LS",
    "wof:name":"Berea Hills",
    "wof:placetype":"locality"
},
  "geometry": {"coordinates":[27.6103,-29.26913],"type":"Point"}
}