{
  "type": "Feature",
  "properties": {
    "gn:admin1_code":"16.0",
    "gn:asciiname":"Liqhobong",
    "gn:country_code":"LS",
    "gn:dem":2427,
    "gn:feature_class":"P",
    "gn:feature_code":"PPL",
    "gn:name":"Liqhobong",
    "gn:population":0,
    "gn:timezone":"Africa/Maseru",
    "iso:country":"LS",
    "name:ukr_x_preferred":[
        "\u041b\u0456\u0445\u043e\u0431\u043e\u043d\u0433"
    ],
    "wof:name":"Liqhobong",
    "wof:placetype":"locality"
},
  "geometry": {"coordinates":[28.59866,-28.9876],"type":"Point"}
}