{
  "type": "Feature",
  "properties": {
    "gn:admin1_code":"14.0",
    "gn:asciiname":"Ha Phohleli",
    "gn:country_code":"LS",
    "gn:dem":1630,
    "gn:feature_class":"P",
    "gn:feature_code":"PPL",
    "gn:name":"Ha Phohleli",
    "gn:population":0,
    "gn:timezone":"Africa/Maseru",
    "iso:country":"LS",
    "wof:name":"Ha Phohleli",
    "wof:placetype":"locality"
},
  "geometry": {"coordinates":[27.63008,-29.51522000000001],"type":"Point"}
}