{
  "type": "Feature",
  "properties": {
    "gn:admin1_code":"13.0",
    "gn:asciiname":"Ha Sebaki",
    "gn:country_code":"LS",
    "gn:dem":1838,
    "gn:feature_class":"P",
    "gn:feature_code":"PPL",
    "gn:name":"Ha Sebaki",
    "gn:population":0,
    "gn:timezone":"Africa/Maseru",
    "iso:country":"LS",
    "wof:name":"Ha Sebaki",
    "wof:placetype":"locality"
},
  "geometry": {"coordinates":[27.465,-29.919],"type":"Point"}
}