{
  "type": "Feature",
  "properties": {
    "gn:admin1_code":"0.0",
    "gn:asciiname":"Matsieng",
    "gn:country_code":"LS",
    "gn:dem":1818,
    "gn:feature_class":"P",
    "gn:feature_code":"PPL",
    "gn:name":"Matsieng",
    "gn:population":0,
    "gn:timezone":"Africa/Maseru",
    "iso:country":"LS",
    "wof:name":"Matsieng",
    "wof:placetype":"locality"
},
  "geometry": {"coordinates":[27.56645,-29.61715],"type":"Point"}
}