{
  "type": "Feature",
  "properties": {
    "gn:admin1_code":"0.0",
    "gn:asciiname":"Kolonyama",
    "gn:cc2":"LS",
    "gn:country_code":"LS",
    "gn:dem":1639,
    "gn:feature_class":"P",
    "gn:feature_code":"PPL",
    "gn:name":"Kolonyama",
    "gn:population":0,
    "gn:timezone":"Africa/Maseru",
    "iso:country":"LS",
    "name:und_x_variant":[
        "Manama",
        "Kolonyama"
    ],
    "wof:name":"Kolonyama",
    "wof:placetype":"locality"
},
  "geometry": {"coordinates":[27.73308,-29.06506],"type":"Point"}
}