{
  "type": "Feature",
  "properties": {
    "gn:admin1_code":"12.0",
    "gn:asciiname":"Mankoaneng",
    "gn:country_code":"LS",
    "gn:dem":1654,
    "gn:feature_class":"P",
    "gn:feature_code":"PPL",
    "gn:name":"Mankoaneng",
    "gn:population":0,
    "gn:timezone":"Africa/Maseru",
    "iso:country":"LS",
    "wof:name":"Mankoaneng",
    "wof:placetype":"locality"
},
  "geometry": {"coordinates":[28.04039,-28.8687],"type":"Point"}
}