{
  "type": "Feature",
  "properties": {
    "gn:admin1_code":"11.0",
    "gn:asciiname":"Ha Molapo",
    "gn:country_code":"LS",
    "gn:dem":1821,
    "gn:feature_class":"P",
    "gn:feature_code":"PPL",
    "gn:name":"Ha Molapo",
    "gn:population":0,
    "gn:timezone":"Africa/Maseru",
    "iso:country":"LS",
    "wof:name":"Ha Molapo",
    "wof:placetype":"locality"
},
  "geometry": {"coordinates":[28.47123,-28.74618],"type":"Point"}
}