{
  "type": "Feature",
  "properties": {
    "gn:admin1_code":"0.0",
    "gn:asciiname":"Boqate",
    "gn:country_code":"LS",
    "gn:dem":1623,
    "gn:feature_class":"P",
    "gn:feature_code":"PPL",
    "gn:name":"Boqate",
    "gn:population":0,
    "gn:timezone":"Africa/Maseru",
    "iso:country":"LS",
    "name:und_x_variant":[
        "Bokatis Store",
        "Boqate"
    ],
    "wof:name":"Boqate",
    "wof:placetype":"locality"
},
  "geometry": {"coordinates":[27.5885,-29.3549],"type":"Point"}
}