{
  "type": "Feature",
  "properties": {
    "gn:admin1_code":"0.0",
    "gn:asciiname":"Nyane",
    "gn:country_code":"LS",
    "gn:dem":2254,
    "gn:feature_class":"P",
    "gn:feature_code":"PPL",
    "gn:name":"Nyane",
    "gn:population":0,
    "gn:timezone":"Africa/Maseru",
    "iso:country":"LS",
    "name:und_x_variant":[
        "Saint Anne of Auray",
        "Nyane"
    ],
    "wof:name":"Nyane",
    "wof:placetype":"locality"
},
  "geometry": {"coordinates":[28.23991,-29.58096],"type":"Point"}
}