{
  "type": "Feature",
  "properties": {
    "iso:country":"LS",
    "label:eng_x_preferred_longname":[
        "Malingoaneng County"
    ],
    "label:eng_x_preferred_placetype":[
        "county"
    ],
    "name:eng_x_preferred":[
        "Malingoaneng"
    ],
    "name:fra_x_preferred":[
        "Malingoaneng"
    ],
    "qs:gn_pop":0,
    "qs:name":"Malingoaneng",
    "qs:name_adm0":"Lesotho",
    "qs:name_adm1":"Mokhotlong",
    "qs:photos":45,
    "qs:photos_1k":9,
    "qs:photos_9k":1,
    "qs:photos_9r":2,
    "qs:photos_all":45,
    "qs:photos_sr":2,
    "qs:placetype":"County",
    "qs:pop_sr":"0",
    "qs:woe_adm0":23424880,
    "wof:name":"Malingoaneng",
    "wof:placetype":"county"
},
  "geometry": {"coordinates":[28.725128,-28.904334],"type":"Point"}
}