{
  "type": "Feature",
  "properties": {
    "gn:admin1_code":"0.0",
    "gn:asciiname":"Kaphe",
    "gn:country_code":"LS",
    "gn:dem":1967,
    "gn:feature_class":"P",
    "gn:feature_code":"PPL",
    "gn:name":"Kaphe",
    "gn:population":0,
    "gn:timezone":"Africa/Maseru",
    "iso:country":"LS",
    "name:und_x_variant":[
        "Kapi",
        "Kaphe"
    ],
    "wof:name":"Kaphe",
    "wof:placetype":"locality"
},
  "geometry": {"coordinates":[27.64088,-29.95565],"type":"Point"}
}