{
  "type": "Feature",
  "properties": {
    "gn:admin1_code":"0.0",
    "gn:asciiname":"Koali",
    "gn:country_code":"LS",
    "gn:dem":1714,
    "gn:feature_class":"P",
    "gn:feature_code":"PPL",
    "gn:name":"Koali",
    "gn:population":0,
    "gn:timezone":"Africa/Maseru",
    "iso:country":"LS",
    "name:und_x_variant":[
        "Koadi",
        "Makoalis",
        "Koali"
    ],
    "wof:name":"Koali",
    "wof:placetype":"locality"
},
  "geometry": {"coordinates":[27.76669,-29.20476],"type":"Point"}
}