{
  "type": "Feature",
  "properties": {
    "gn:admin1_code":"0.0",
    "gn:asciiname":"Thaba Putsoa",
    "gn:country_code":"LS",
    "gn:dem":2384,
    "gn:feature_class":"P",
    "gn:feature_code":"PPL",
    "gn:name":"Thaba Putsoa",
    "gn:population":0,
    "gn:timezone":"Africa/Maseru",
    "iso:country":"LS",
    "wof:name":"Thaba Putsoa",
    "wof:placetype":"locality"
},
  "geometry": {"coordinates":[28.06095,-29.59367],"type":"Point"}
}