{
  "type": "Feature",
  "properties": {
    "gn:admin1_code":"0.0",
    "gn:asciiname":"Qamako",
    "gn:country_code":"LS",
    "gn:dem":1754,
    "gn:feature_class":"P",
    "gn:feature_code":"PPL",
    "gn:name":"Qamako",
    "gn:population":0,
    "gn:timezone":"Africa/Maseru",
    "iso:country":"LS",
    "name:und_x_variant":[
        "Thabatsoeu",
        "Qamako"
    ],
    "wof:name":"Qamako",
    "wof:placetype":"locality"
},
  "geometry": {"coordinates":[27.40898,-29.78468],"type":"Point"}
}