{
  "type": "Feature",
  "properties": {
    "gn:admin1_code":"0.0",
    "gn:asciiname":"Mokoroane",
    "gn:country_code":"LS",
    "gn:dem":1690,
    "gn:feature_class":"P",
    "gn:feature_code":"PPL",
    "gn:name":"Mokoroane",
    "gn:population":0,
    "gn:timezone":"Africa/Maseru",
    "iso:country":"LS",
    "wof:name":"Mokoroane",
    "wof:placetype":"locality"
},
  "geometry": {"coordinates":[27.21481,-29.92369],"type":"Point"}
}