{
  "type": "Feature",
  "properties": {
    "gn:admin1_code":"0.0",
    "gn:asciiname":"Mabotse",
    "gn:country_code":"LS",
    "gn:dem":1471,
    "gn:feature_class":"P",
    "gn:feature_code":"PPL",
    "gn:name":"Mabotse",
    "gn:population":0,
    "gn:timezone":"Africa/Maseru",
    "iso:country":"LS",
    "name:und_x_variant":[
        "Mabotsi",
        "Mabotse"
    ],
    "wof:name":"Mabotse",
    "wof:placetype":"locality"
},
  "geometry": {"coordinates":[27.06723,-29.64353],"type":"Point"}
}