{
  "type": "Feature",
  "properties": {
    "gn:admin1_code":"10.0",
    "gn:asciiname":"Koalabata",
    "gn:country_code":"LS",
    "gn:dem":1597,
    "gn:feature_class":"P",
    "gn:feature_code":"PPL",
    "gn:name":"Koalabata",
    "gn:population":0,
    "gn:timezone":"Africa/Maseru",
    "iso:country":"LS",
    "wof:name":"Koalabata",
    "wof:placetype":"locality"
},
  "geometry": {"coordinates":[27.55698,-29.29676],"type":"Point"}
}