{
  "type": "Feature",
  "properties": {
    "gn:admin1_code":"0.0",
    "gn:asciiname":"Tsupane Gate",
    "gn:country_code":"LS",
    "gn:dem":1540,
    "gn:feature_class":"P",
    "gn:feature_code":"PPL",
    "gn:name":"Tsupane Gate",
    "gn:population":0,
    "gn:timezone":"Africa/Maseru",
    "iso:country":"LS",
    "name:und_x_variant":[
        "Sepanies Gate",
        "Tsupani Gate",
        "Tsupane Gate"
    ],
    "wof:name":"Tsupane Gate",
    "wof:placetype":"locality"
},
  "geometry": {"coordinates":[27.09854,-29.7071],"type":"Point"}
}