{
  "type": "Feature",
  "properties": {
    "gn:admin1_code":"0.0",
    "gn:asciiname":"Ha Senekane",
    "gn:cc2":"LS",
    "gn:country_code":"LS",
    "gn:dem":1827,
    "gn:feature_class":"P",
    "gn:feature_code":"PPL",
    "gn:name":"Ha Senekane",
    "gn:population":0,
    "gn:timezone":"Africa/Maseru",
    "iso:country":"LS",
    "name:und_x_variant":[
        "Senekals",
        "Senekal"
    ],
    "wof:name":"Ha Senekane",
    "wof:placetype":"locality"
},
  "geometry": {"coordinates":[27.72765,-29.2554],"type":"Point"}
}