{
  "type": "Feature",
  "properties": {
    "gn:admin1_code":"0.0",
    "gn:asciiname":"Mokonyane",
    "gn:country_code":"LS",
    "gn:dem":1803,
    "gn:feature_class":"P",
    "gn:feature_code":"PPL",
    "gn:name":"Mokonyane",
    "gn:population":0,
    "gn:timezone":"Africa/Maseru",
    "iso:country":"LS",
    "name:und_x_variant":[
        "Mokunyane",
        "Mokonyane"
    ],
    "wof:name":"Mokonyane",
    "wof:placetype":"locality"
},
  "geometry": {"coordinates":[27.85867,-29.28832],"type":"Point"}
}