{
  "type": "Feature",
  "properties": {
    "gn:admin1_code":"0.0",
    "gn:asciiname":"Mathokoane",
    "gn:country_code":"LS",
    "gn:dem":1682,
    "gn:feature_class":"P",
    "gn:feature_code":"PPL",
    "gn:name":"Mathokoane",
    "gn:population":0,
    "gn:timezone":"Africa/Maseru",
    "iso:country":"LS",
    "name:und_x_variant":[
        "Peete Molapo",
        "Mathokoane"
    ],
    "wof:name":"Mathokoane",
    "wof:placetype":"locality"
},
  "geometry": {"coordinates":[28.02778,-28.97246],"type":"Point"}
}