{
  "type": "Feature",
  "properties": {
    "gn:admin1_code":"0.0",
    "gn:asciiname":"Morifi",
    "gn:country_code":"LS",
    "gn:dem":1454,
    "gn:feature_class":"P",
    "gn:feature_code":"PPL",
    "gn:name":"Morifi",
    "gn:population":0,
    "gn:timezone":"Africa/Maseru",
    "iso:country":"LS",
    "name:und_x_variant":[
        "Morife",
        "Morife Store",
        "Morifi"
    ],
    "wof:name":"Morifi",
    "wof:placetype":"locality"
},
  "geometry": {"coordinates":[27.40383,-30.30249],"type":"Point"}
}