{
  "type": "Feature",
  "properties": {
    "gn:admin1_code":"10.0",
    "gn:asciiname":"Ha Ramonaheng",
    "gn:country_code":"LS",
    "gn:dem":1711,
    "gn:feature_class":"P",
    "gn:feature_code":"PPL",
    "gn:name":"Ha Ramonaheng",
    "gn:population":0,
    "gn:timezone":"Africa/Maseru",
    "iso:country":"LS",
    "wof:name":"Ha Ramonaheng",
    "wof:placetype":"locality"
},
  "geometry": {"coordinates":[27.74166,-29.15139000000001],"type":"Point"}
}