{
  "type": "Feature",
  "properties": {
    "gn:admin1_code":"0.0",
    "gn:asciiname":"Mpharane",
    "gn:country_code":"LS",
    "gn:dem":1670,
    "gn:feature_class":"P",
    "gn:feature_code":"PPL",
    "gn:name":"Mpharane",
    "gn:population":0,
    "gn:timezone":"Africa/Maseru",
    "iso:country":"LS",
    "wof:name":"Mpharane",
    "wof:placetype":"locality"
},
  "geometry": {"coordinates":[27.55,-30.01667],"type":"Point"}
}